{
    "name": "Tera-Pkt-Item-Skill-Logger",
    "title": "Tera Pkt Item Skill Logger",
    "author": "<font color='#297229'>merusira</font>",
    "description": "Logs all incoming and outgoing network packets to the chat and parses to a file. Includes item and skill logging with names and IDs.",
    "version": "<font color='#800000'>1.3.0</font>",
    "servers": ["https://raw.githubusercontent.com/merusira/tera-pkt-item-skill-logger/master/"],
    "supportUrl": "https://github.com/merusira/tera-pkt-item-skill-logger/issues",
    "dependencies": {
        "command": "https://raw.githubusercontent.com/tera-toolbox/command/master/module.json"
    },
    "options": {
        "guiName": "<font color='#7558cd'>Pkt Item Skill Logger</font>",
        "cliName": "<font color='#7558cd'>pkt-item-skill-logger</font>",
        "settingsVersion": 2,
		"settingsMigrator": "settings_migrator.js"
    },
    "disableAutoUpdate": false,
    "disabled": false
}